{"tagline":"My personal project report.","google":"","note":"Don't delete this file! It's used internally to help with page regeneration.","name":"Personal Project Report","body":"### Requirements\r\n\r\nTo render this document, a LaTeX software package is required. This\r\ndocument was rendered on my machine using MacTeX (available\r\n[here](http://www.tug.org/mactex/2011/)).\r\n\r\n### Compiling and Rendering\r\n\r\nTo compile and render this document, download the document as a zip file\r\nabove and then run the following commands from the root directory of the project:\r\n\r\n```\r\n$ cd LaTeX\r\n$ make render\r\n```"}